{
  "denhaag": {
    "process-steps": {
      "font-family": { "value": "{denhaag.typography.sans-serif.font-family}" },
      "font-size": { "value": "{denhaag.typography.scale.base.font-size}" },
      "line-height": { "value": "24px" },
      "step-marker": {
        "background-color": { "value": "{denhaag.color.grey.1}" },
        "color": { "value": "{denhaag.color.grey.4}" },
        "margin": { "value": "auto" },
        "padding": { "value": "12px" },
        "size": { "value": "20px" },
        "checked": {
          "background-color": { "value": "{denhaag.color.white}" },
          "border-color": { "value": "{denhaag.color.green.3}" },
          "color": { "value": "{denhaag.color.green.3}" }
        },
        "current": {
          "background-color": { "value": "{denhaag.color.green.3}" },
          "color": { "value": "{denhaag.color.white}" }
        },
        "not-checked": {
          "color": { "value": "{denhaag.color.grey.2}" }
        },
        "text": {
          "active": {
            "color": { "value": "{denhaag.color.white}" }
          }
        }
      },
      "step-heading": {
        "color": { "value": "{denhaag.color.grey.4}" },
        "font-size": { "value": "{denhaag.typography.scale.base.font-size}" },
        "font-weight": { "value": "{denhaag.typography.weight.bold}" },
        "line-height": { "value": "{denhaag.typography.scale.base.line-height}" },
        "checked": {
          "font-size": { "value": "{denhaag.typography.scale.base.font-size}" },
          "font-weight": { "value": "{denhaag.typography.weight.bold}" },
          "line-height": { "value": "{denhaag.typography.scale.base.line-height}" }
        },
        "current": {
          "color": { "value": "{denhaag.color.green.3}" },
          "font-size": { "value": "{denhaag.typography.scale.base.font-size}" },
          "font-weight": { "value": "{denhaag.typography.weight.bold}" },
          "line-height": { "value": "{denhaag.typography.scale.base.line-height}" }
        }
      },
      "step-collapse-icon": {
        "size": { "value": "16px" },
        "padding": { "value": "4px" }
      },
      "step-content": {
        "color": { "value": "{denhaag.color.grey.4}" },
        "margin": { "value": "12px" }
      },
      "step-marker-text": {
        "font-size": { "value": "{denhaag.typography.scale.s.font-size}" }
      },
      "step": {
        "outline-offset": { "value": "2px" },
        "outline": { "value": "{denhaag.focus.border}" },
        "padding": { "value": "12px" }
      },
      "sub-step-marker": {
        "background-color": { "value": "{denhaag.color.grey.1}" },
        "border-color": { "value": "{denhaag.color.grey.4}" }
      }
    }
  }
}
